{
    "client": "Thunder Client",
    "collectionName": "categoriesCollection",
    "dateExported": "2024-03-09T05:52:30.181Z",
    "version": "1.1",
    "folders": [],
    "requests": [
        {
            "_id": "4e0a67ff-b274-428c-bd11-c2c20cc8a47b",
            "colId": "7d36ab37-8909-4d5f-b7a3-f3d992419f81",
            "containerId": "",
            "name": "newCategory",
            "url": "http://localhost:8080/taller_proyectof_bim1/v1/categories",
            "method": "POST",
            "sortNum": 10000,
            "created": "2024-03-07T22:44:04.353Z",
            "modified": "2024-03-09T05:46:38.087Z",
            "headers": [
                {
                    "name": "x-token",
                    "value": ""
                }
            ],
            "params": [],
            "body": {
                "type": "json",
                "raw": "{\n  \"name\":\"ChocolatesTest\",\n  \"description\":\"Chocolates from Guatemala\"\n}",
                "form": []
            },
            "reqType": "post",
            "tests": []
        },
        {
            "_id": "43e1b4e7-1adb-4161-acbb-88e4100220f5",
            "colId": "7d36ab37-8909-4d5f-b7a3-f3d992419f81",
            "containerId": "",
            "name": "viewCategories",
            "url": "http://localhost:8080/taller_proyectof_bim1/v1/categories?from=0&limit=4",
            "method": "GET",
            "sortNum": 20000,
            "created": "2024-03-07T22:44:04.354Z",
            "modified": "2024-03-09T03:56:41.011Z",
            "headers": [],
            "params": [
                {
                    "name": "from",
                    "value": "0",
                    "isPath": false
                },
                {
                    "name": "limit",
                    "value": "4",
                    "isPath": false
                }
            ],
            "reqType": "get",
            "tests": []
        },
        {
            "_id": "938f6eca-a350-4f2f-ab0d-a632ee8dd5df",
            "colId": "7d36ab37-8909-4d5f-b7a3-f3d992419f81",
            "containerId": "",
            "name": "putCategory",
            "url": "http://localhost:8080/taller_proyectof_bim1/v1/categories/65e77cfdf9d98f9b2481bcb5",
            "method": "PUT",
            "sortNum": 30000,
            "created": "2024-03-07T22:44:04.355Z",
            "modified": "2024-03-09T05:46:42.551Z",
            "headers": [
                {
                    "name": "x-token",
                    "value": ""
                }
            ],
            "params": [],
            "body": {
                "type": "json",
                "raw": "{\n  \"description\":\"Candies imported from Mexico\"\n}",
                "form": []
            },
            "reqType": "put",
            "tests": []
        },
        {
            "_id": "4b9e681c-d171-4ac9-bfaf-de416d2fb6ee",
            "colId": "7d36ab37-8909-4d5f-b7a3-f3d992419f81",
            "containerId": "",
            "name": "deleteCategory",
            "url": "http://localhost:8080/taller_proyectof_bim1/v1/categories/65ebe7a46db9659287d011a0",
            "method": "DELETE",
            "sortNum": 40000,
            "created": "2024-03-07T22:44:04.356Z",
            "modified": "2024-03-09T05:46:46.825Z",
            "headers": [
                {
                    "name": "x-token",
                    "value": ""
                }
            ],
            "params": [],
            "reqType": "del",
            "tests": []
        }
    ]
}